powersupply/__init__.py
powersupply/__main__.py
powersupply/platform.py
powersupply/platform_internals.py
powersupply/powersupply.glade
powersupply-0.5.0.dist-info/LICENSE
powersupply-0.5.0.dist-info/METADATA
powersupply-0.5.0.dist-info/WHEEL
powersupply-0.5.0.dist-info/entry_points.txt
powersupply-0.5.0.dist-info/top_level.txt
powersupply-0.5.0.dist-info/zip-safe
powersupply-0.5.0.dist-info/RECORD
