Metadata-Version: 2.1
Name: powersupply
Version: 0.5.0
Summary: Tool to display the detailed power status of the PinePhone
Home-page: https://gitlab.com/MartijnBraam/powersupply
Author: Martijn Braam
Author-email: martijn@brixit.nl
License: MIT
Platform: UNKNOWN
Classifier: License :: OSI Approved :: MIT License
Classifier: Programming Language :: Python :: 3.8
Classifier: Operating System :: POSIX :: Linux
